[{"src":"resource/qdati/F2xAuto_153.mp3?v=30","type":"sound","id":"F2xAuto_153"},{"src":"resource/qdati/F2xAuto_154.mp3?v=30","type":"sound","id":"F2xAuto_154"},{"src":"resource/qdati/SpecialSound.mp3?v=30","type":"sound","id":"SpecialSound"},{"src":"resource/qdati/F2xAuto_221.jpg?v=30","type":"image","id":"F2xAuto_221"},{"src":"resource/qdati/F2xSSIMG0.png?v=30","type":"image","id":"F2xSSIMG0"},{"src":"resource/qdati/F2xSSIMG0.json?v=30","type":"text","id":"F2xSSIMGData0"},{"src":"src/qdati/qdatiAuto.js?v=30","type":"javascript"},{"isStage":true,"src":"src/qdati/Topic.js?v=30","type":"javascript"},{"src":"src/qdati/Choice_box.js?v=30","type":"javascript"},{"src":"src/qdati/Photo.js?v=30","type":"javascript"},{"src":"src/qdati/D.js?v=30","type":"javascript"},{"src":"src/qdati/C.js?v=30","type":"javascript"},{"src":"src/qdati/B.js?v=30","type":"javascript"},{"src":"src/qdati/A.js?v=30","type":"javascript"},{"src":"src/qdati/Topic_txt.js?v=30","type":"javascript"},{"src":"src/qdati/Home.js?v=30","type":"javascript"},{"src":"src/qdati/Title.js?v=30","type":"javascript"},{"src":"src/qdati/Title_txt.js?v=30","type":"javascript"}]